{
  "schema": 1,
  "module": "/home/mangelo/Documents/GitHub/xhdfe/build_cuda/py_hdfe_v11.cpython-312-x86_64-linux-gnu.so",
  "module_sha256": "4e642d5eae1f2e43a5adcc898533019f9be398196c683e0dcef430b4d6fa12a1",
  "backend_requested": "cuda",
  "mode": "absorbed",
  "round": 6,
  "n": 500000,
  "threads": 16,
  "inner_reps": 3,
  "load_at_end": [
    31.35,
    31.51,
    32.46
  ],
  "samples": {
    "unadjusted/unw": [
      {
        "inner": 0,
        "seconds": 0.17820795252919197,
        "identity_gap": 1.1937117960769683e-12,
        "notes": "absorbed FE blocks use the aux-regression (gamma0) variance. declared absorbed-target coefficients in the full model are imposed at zero, not estimated. WARNING: absorbed-target inference is not certified for this VCE. Use vce(cluster) with clusters equal to an FE dimension that absorbs every declared target; unadjusted, robust, or crossed clustering can be anti-conservative. ",
        "gpu_requested": true,
        "gpu_used": true,
        "gpu_backend": "cuda",
        "gpu_status": "used"
      },
      {
        "inner": 1,
        "seconds": 0.1265740804374218,
        "identity_gap": 1.1937117960769683e-12,
        "notes": "absorbed FE blocks use the aux-regression (gamma0) variance. declared absorbed-target coefficients in the full model are imposed at zero, not estimated. WARNING: absorbed-target inference is not certified for this VCE. Use vce(cluster) with clusters equal to an FE dimension that absorbs every declared target; unadjusted, robust, or crossed clustering can be anti-conservative. ",
        "gpu_requested": true,
        "gpu_used": true,
        "gpu_backend": "cuda",
        "gpu_status": "used"
      },
      {
        "inner": 2,
        "seconds": 0.13413843512535095,
        "identity_gap": 1.1937117960769683e-12,
        "notes": "absorbed FE blocks use the aux-regression (gamma0) variance. declared absorbed-target coefficients in the full model are imposed at zero, not estimated. WARNING: absorbed-target inference is not certified for this VCE. Use vce(cluster) with clusters equal to an FE dimension that absorbs every declared target; unadjusted, robust, or crossed clustering can be anti-conservative. ",
        "gpu_requested": true,
        "gpu_used": true,
        "gpu_backend": "cuda",
        "gpu_status": "used"
      }
    ],
    "unadjusted/w": [
      {
        "inner": 0,
        "seconds": 0.15339883789420128,
        "identity_gap": 1.789624004544521e-12,
        "notes": "absorbed FE blocks use the aux-regression (gamma0) variance. declared absorbed-target coefficients in the full model are imposed at zero, not estimated. WARNING: absorbed-target inference is not certified for this VCE. Use vce(cluster) with clusters equal to an FE dimension that absorbs every declared target; unadjusted, robust, or crossed clustering can be anti-conservative. ",
        "gpu_requested": true,
        "gpu_used": true,
        "gpu_backend": "cuda",
        "gpu_status": "used"
      },
      {
        "inner": 1,
        "seconds": 0.14501988142728806,
        "identity_gap": 1.789624004544521e-12,
        "notes": "absorbed FE blocks use the aux-regression (gamma0) variance. declared absorbed-target coefficients in the full model are imposed at zero, not estimated. WARNING: absorbed-target inference is not certified for this VCE. Use vce(cluster) with clusters equal to an FE dimension that absorbs every declared target; unadjusted, robust, or crossed clustering can be anti-conservative. ",
        "gpu_requested": true,
        "gpu_used": true,
        "gpu_backend": "cuda",
        "gpu_status": "used"
      },
      {
        "inner": 2,
        "seconds": 0.15794289484620094,
        "identity_gap": 1.7897905379982149e-12,
        "notes": "absorbed FE blocks use the aux-regression (gamma0) variance. declared absorbed-target coefficients in the full model are imposed at zero, not estimated. WARNING: absorbed-target inference is not certified for this VCE. Use vce(cluster) with clusters equal to an FE dimension that absorbs every declared target; unadjusted, robust, or crossed clustering can be anti-conservative. ",
        "gpu_requested": true,
        "gpu_used": true,
        "gpu_backend": "cuda",
        "gpu_status": "used"
      }
    ],
    "cluster/unw": [
      {
        "inner": 0,
        "seconds": 0.2098938189446926,
        "identity_gap": 1.1368683772161603e-12,
        "notes": "absorbed FE blocks use the aux-regression (gamma0) variance. declared absorbed-target coefficients in the full model are imposed at zero, not estimated. absorbed-target inference is clustered at an FE dimension that absorbs every declared target. ",
        "gpu_requested": true,
        "gpu_used": true,
        "gpu_backend": "cuda",
        "gpu_status": "used"
      },
      {
        "inner": 1,
        "seconds": 0.17260584235191345,
        "identity_gap": 1.1368683772161603e-12,
        "notes": "absorbed FE blocks use the aux-regression (gamma0) variance. declared absorbed-target coefficients in the full model are imposed at zero, not estimated. absorbed-target inference is clustered at an FE dimension that absorbs every declared target. ",
        "gpu_requested": true,
        "gpu_used": true,
        "gpu_backend": "cuda",
        "gpu_status": "used"
      },
      {
        "inner": 2,
        "seconds": 0.18970433622598648,
        "identity_gap": 1.1368683772161603e-12,
        "notes": "absorbed FE blocks use the aux-regression (gamma0) variance. declared absorbed-target coefficients in the full model are imposed at zero, not estimated. absorbed-target inference is clustered at an FE dimension that absorbs every declared target. ",
        "gpu_requested": true,
        "gpu_used": true,
        "gpu_backend": "cuda",
        "gpu_status": "used"
      }
    ],
    "cluster/w": [
      {
        "inner": 0,
        "seconds": 0.2330014891922474,
        "identity_gap": 1.7911783167789963e-12,
        "notes": "absorbed FE blocks use the aux-regression (gamma0) variance. declared absorbed-target coefficients in the full model are imposed at zero, not estimated. absorbed-target inference is clustered at an FE dimension that absorbs every declared target. ",
        "gpu_requested": true,
        "gpu_used": true,
        "gpu_backend": "cuda",
        "gpu_status": "used"
      },
      {
        "inner": 1,
        "seconds": 0.20861278101801872,
        "identity_gap": 1.7914003613839213e-12,
        "notes": "absorbed FE blocks use the aux-regression (gamma0) variance. declared absorbed-target coefficients in the full model are imposed at zero, not estimated. absorbed-target inference is clustered at an FE dimension that absorbs every declared target. ",
        "gpu_requested": true,
        "gpu_used": true,
        "gpu_backend": "cuda",
        "gpu_status": "used"
      },
      {
        "inner": 2,
        "seconds": 0.23947909846901894,
        "identity_gap": 1.7914003613839213e-12,
        "notes": "absorbed FE blocks use the aux-regression (gamma0) variance. declared absorbed-target coefficients in the full model are imposed at zero, not estimated. absorbed-target inference is clustered at an FE dimension that absorbs every declared target. ",
        "gpu_requested": true,
        "gpu_used": true,
        "gpu_backend": "cuda",
        "gpu_status": "used"
      }
    ]
  }
}
